pywindow/__init__.py
pywindow/py.typed
pywindow/_internal/__init__.py
pywindow/_internal/io_tools.py
pywindow/_internal/molecular.py
pywindow/_internal/tables.py
pywindow/_internal/trajectory.py
pywindow/_internal/utilities.py
pywindowx-2025.9.29.0.dist-info/licenses/LICENSE
pywindowx-2025.9.29.0.dist-info/METADATA
pywindowx-2025.9.29.0.dist-info/WHEEL
pywindowx-2025.9.29.0.dist-info/top_level.txt
pywindowx-2025.9.29.0.dist-info/RECORD
