Metadata-Version: 2.4
Name: pywindowx
Version: 2025.9.29.0
Summary:  A Python package for structural analysis of porous molecules.
Maintainer-email: Marcin Miklitz <marcin.miklitz@gmail.com>, Andrew Tarzia <andrew.tarzia@gmail.com>
Project-URL: github, https://github.com/marcinmiklitz/pywindow
Project-URL: documentation, https://pywindow.readthedocs.io
Requires-Python: >=3.9
License-File: LICENSE
Requires-Dist: numpy
Requires-Dist: scipy
Requires-Dist: scikit-learn
Requires-Dist: rdkit
Requires-Dist: matplotlib
Provides-Extra: dev
Requires-Dist: ruff; extra == "dev"
Requires-Dist: mypy; extra == "dev"
Requires-Dist: pip-tools; extra == "dev"
Requires-Dist: pytest<8; extra == "dev"
Requires-Dist: pytest-datadir; extra == "dev"
Requires-Dist: pytest-lazy-fixture; extra == "dev"
Requires-Dist: pytest-cov; extra == "dev"
Requires-Dist: sphinx; extra == "dev"
Requires-Dist: sphinx-copybutton; extra == "dev"
Requires-Dist: twine; extra == "dev"
Requires-Dist: sphinx_rtd_theme; extra == "dev"
Requires-Dist: furo; extra == "dev"
Requires-Dist: moldoc; extra == "dev"
Dynamic: license-file
